cgmes2pgm_suite/__init__.py
cgmes2pgm_suite/__main__.py
cgmes2pgm_suite/app.py
cgmes2pgm_suite/common/__init__.py
cgmes2pgm_suite/common/cgmes_classes.py
cgmes2pgm_suite/common/input_data_tools.py
cgmes2pgm_suite/common/node_balance.py
cgmes2pgm_suite/config/__init__.py
cgmes2pgm_suite/config/config.py
cgmes2pgm_suite/config/reader.py
cgmes2pgm_suite/export/__init__.py
cgmes2pgm_suite/export/iri_export.py
cgmes2pgm_suite/export/measurement_export.py
cgmes2pgm_suite/export/measurment_analysis.py
cgmes2pgm_suite/export/node_balance_export.py
cgmes2pgm_suite/export/pgm_export.py
cgmes2pgm_suite/export/result_text_export.py
cgmes2pgm_suite/export/ssh_substitution_export.py
cgmes2pgm_suite/export/sv_builder.py
cgmes2pgm_suite/export/text_export.py
cgmes2pgm_suite/export/xml_export.py
cgmes2pgm_suite/export/excel/__init__.py
cgmes2pgm_suite/export/excel/abstract_result_sheet_writer.py
cgmes2pgm_suite/export/excel/branch_sheet_writer.py
cgmes2pgm_suite/export/excel/documentation_writer.py
cgmes2pgm_suite/export/excel/excel_export.py
cgmes2pgm_suite/export/excel/excel_sheet_writer.py
cgmes2pgm_suite/export/excel/meas_sheet_writer.py
cgmes2pgm_suite/export/excel/node_sheet_writer.py
cgmes2pgm_suite/export/excel/summary_sheet_writer.py
cgmes2pgm_suite/export/excel/sv_comparison_sheet_writer.py
cgmes2pgm_suite/export/utils/__init__.py
cgmes2pgm_suite/export/utils/current_measurement.py
cgmes2pgm_suite/export/utils/format_df.py
cgmes2pgm_suite/export/utils/sv_lookup.py
cgmes2pgm_suite/export/utils/unit_converter.py
cgmes2pgm_suite/export/utils/xml_builder.py
cgmes2pgm_suite/measurement_simulation/__init__.py
cgmes2pgm_suite/measurement_simulation/meas_ranges.py
cgmes2pgm_suite/measurement_simulation/measurement_builder.py
cgmes2pgm_suite/measurement_simulation/power_measurement_builder.py
cgmes2pgm_suite/measurement_simulation/value_source_builder.py
cgmes2pgm_suite/measurement_simulation/voltage_measurement_builder.py
cgmes2pgm_suite/rdf_store/__init__.py
cgmes2pgm_suite-0.4.3.dist-info/licenses/LICENSE
cgmes2pgm_suite-0.4.3.dist-info/METADATA
cgmes2pgm_suite-0.4.3.dist-info/WHEEL
cgmes2pgm_suite-0.4.3.dist-info/top_level.txt
cgmes2pgm_suite-0.4.3.dist-info/RECORD
