Metadata-Version: 2.4
Name: cgmes2pgm_suite
Version: 0.4.3
Summary: Additional tools for cgmes2pgm_converter to integrate PowerGridModel with the Common Grid Model Exchange Standard (CGMES)
Author-email: "Lars Friedrich, Eduard Fried, Udo Schmitz" <powergridmodel@soptim.de>
License-Expression: Apache-2.0
Project-URL: Homepage, https://github.com/SOPTIM/cgmes2pgm_suite
Project-URL: Repository, https://github.com/SOPTIM/cgmes2pgm_suite
Project-URL: Issues, https://github.com/SOPTIM/cgmes2pgm_suite/issues
Keywords: cgmes,pgm,State Estimation,Power Grid Model
Classifier: Programming Language :: Python :: 3
Classifier: Development Status :: 4 - Beta
Classifier: Intended Audience :: Developers
Classifier: Intended Audience :: Science/Research
Requires-Python: >=3.12.3
License-File: LICENSE
Requires-Dist: bidict~=0.23.1
Requires-Dist: numpy~=2.3.4
Requires-Dist: pandas~=2.3.3
Requires-Dist: power-grid-model~=1.12.60
Requires-Dist: power-grid-model-io~=1.3.26
Requires-Dist: SPARQLWrapper~=2.0.0
Requires-Dist: XlsxWriter~=3.2.9
Requires-Dist: PyYAML~=6.0.3
Requires-Dist: StrEnum~=0.4.15
Requires-Dist: cgmes2pgm_converter~=0.4.3
Requires-Dist: rdflib~=7.4.0
Requires-Dist: docker~=7.1.0
Provides-Extra: dev
Requires-Dist: build>=1.3.0; extra == "dev"
Requires-Dist: ipykernel>=7.1.0; extra == "dev"
Requires-Dist: jupyter-core>=5.9.1; extra == "dev"
Requires-Dist: pre-commit>=4.3.0; extra == "dev"
Requires-Dist: pytest>=8.4.2; extra == "dev"
Requires-Dist: ruff>=0.14.3; extra == "dev"
Requires-Dist: twine>=6.2.0; extra == "dev"
Dynamic: license-file
